{
  "_fv": 66,
  "_type": "loottable",
  "definition": {
    "type": "Chest",
    "pools": [
      {
        "minrolls": 1,
        "maxrolls": 2,
        "minbonusrolls": 1,
        "maxbonusrolls": 4,
        "hasbonusrolls": true,
        "entries": [
          {
            "type": "item",
            "item": {
              "value": "CUSTOM:PiglinTotemScrolls"
            },
            "weight": 1,
            "minCount": 3,
            "maxCount": 6,
            "minEnchantmentLevel": 0,
            "maxEnchantmentLevel": 0,
            "affectedByFortune": false,
            "explosionDecay": false,
            "silkTouchMode": 0
          },
          {
            "type": "item",
            "item": {
              "value": "CUSTOM:ChickenTotemScrolls"
            },
            "weight": 1,
            "minCount": 3,
            "maxCount": 6,
            "minEnchantmentLevel": 0,
            "maxEnchantmentLevel": 0,
            "affectedByFortune": false,
            "explosionDecay": false,
            "silkTouchMode": 0
          },
          {
            "type": "item",
            "item": {
              "value": "CUSTOM:BoshiTotemScrolls"
            },
            "weight": 1,
            "minCount": 3,
            "maxCount": 6,
            "minEnchantmentLevel": 0,
            "maxEnchantmentLevel": 0,
            "affectedByFortune": false,
            "explosionDecay": false,
            "silkTouchMode": 0
          },
          {
            "type": "item",
            "item": {
              "value": "CUSTOM:ChangfuTotemScrolls"
            },
            "weight": 1,
            "minCount": 3,
            "maxCount": 6,
            "minEnchantmentLevel": 0,
            "maxEnchantmentLevel": 0,
            "affectedByFortune": false,
            "explosionDecay": false,
            "silkTouchMode": 0
          },
          {
            "type": "item",
            "item": {
              "value": "CUSTOM:LeiTotemScrolls"
            },
            "weight": 1,
            "minCount": 3,
            "maxCount": 6,
            "minEnchantmentLevel": 0,
            "maxEnchantmentLevel": 0,
            "affectedByFortune": false,
            "explosionDecay": false,
            "silkTouchMode": 0
          },
          {
            "type": "item",
            "item": {
              "value": "CUSTOM:LongChiTotemScrolls"
            },
            "weight": 1,
            "minCount": 3,
            "maxCount": 6,
            "minEnchantmentLevel": 0,
            "maxEnchantmentLevel": 0,
            "affectedByFortune": false,
            "explosionDecay": false,
            "silkTouchMode": 0
          },
          {
            "type": "item",
            "item": {
              "value": "CUSTOM:ZhengTotemScrolls"
            },
            "weight": 1,
            "minCount": 3,
            "maxCount": 6,
            "minEnchantmentLevel": 0,
            "maxEnchantmentLevel": 0,
            "affectedByFortune": false,
            "explosionDecay": false,
            "silkTouchMode": 0
          }
        ]
      },
      {
        "minrolls": 1,
        "maxrolls": 2,
        "minbonusrolls": 0,
        "maxbonusrolls": 1,
        "hasbonusrolls": true,
        "entries": [
          {
            "type": "item",
            "item": {
              "value": "CUSTOM:Greenjade"
            },
            "weight": 1,
            "minCount": 3,
            "maxCount": 8,
            "minEnchantmentLevel": 0,
            "maxEnchantmentLevel": 0,
            "affectedByFortune": false,
            "explosionDecay": false,
            "silkTouchMode": 0
          },
          {
            "type": "item",
            "item": {
              "value": "CUSTOM:Whitejade"
            },
            "weight": 1,
            "minCount": 3,
            "maxCount": 8,
            "minEnchantmentLevel": 0,
            "maxEnchantmentLevel": 0,
            "affectedByFortune": false,
            "explosionDecay": false,
            "silkTouchMode": 0
          },
          {
            "type": "item",
            "item": {
              "value": "CUSTOM:Jadetablet"
            },
            "weight": 1,
            "minCount": 1,
            "maxCount": 1,
            "minEnchantmentLevel": 0,
            "maxEnchantmentLevel": 0,
            "affectedByFortune": false,
            "explosionDecay": false,
            "silkTouchMode": 0
          },
          {
            "type": "item",
            "item": {
              "value": "CUSTOM:JadeCong"
            },
            "weight": 1,
            "minCount": 3,
            "maxCount": 8,
            "minEnchantmentLevel": 0,
            "maxEnchantmentLevel": 0,
            "affectedByFortune": false,
            "explosionDecay": false,
            "silkTouchMode": 0
          },
          {
            "type": "item",
            "item": {
              "value": "CUSTOM:AlgaeJade"
            },
            "weight": 1,
            "minCount": 3,
            "maxCount": 8,
            "minEnchantmentLevel": 0,
            "maxEnchantmentLevel": 0,
            "affectedByFortune": false,
            "explosionDecay": false,
            "silkTouchMode": 0
          },
          {
            "type": "item",
            "item": {
              "value": "CUSTOM:Token"
            },
            "weight": 1,
            "minCount": 1,
            "maxCount": 1,
            "minEnchantmentLevel": 0,
            "maxEnchantmentLevel": 0,
            "affectedByFortune": false,
            "explosionDecay": false,
            "silkTouchMode": 0
          },
          {
            "type": "item",
            "item": {
              "value": "CUSTOM:Jadepiece"
            },
            "weight": 1,
            "minCount": 2,
            "maxCount": 4,
            "minEnchantmentLevel": 0,
            "maxEnchantmentLevel": 0,
            "affectedByFortune": false,
            "explosionDecay": false,
            "silkTouchMode": 0
          },
          {
            "type": "item",
            "item": {
              "value": "Items.IRON_SWORD"
            },
            "weight": 2,
            "minCount": 1,
            "maxCount": 1,
            "minEnchantmentLevel": 1,
            "maxEnchantmentLevel": 3,
            "affectedByFortune": false,
            "explosionDecay": false,
            "silkTouchMode": 0
          }
        ]
      },
      {
        "minrolls": 1,
        "maxrolls": 2,
        "minbonusrolls": 0,
        "maxbonusrolls": 1,
        "hasbonusrolls": true,
        "entries": [
          {
            "type": "item",
            "item": {
              "value": "CUSTOM:BronzeXuan"
            },
            "weight": 1,
            "minCount": 1,
            "maxCount": 3,
            "minEnchantmentLevel": 0,
            "maxEnchantmentLevel": 0,
            "affectedByFortune": false,
            "explosionDecay": false,
            "silkTouchMode": 0
          },
          {
            "type": "item",
            "item": {
              "value": "CUSTOM:Bloodcopperplate"
            },
            "weight": 1,
            "minCount": 3,
            "maxCount": 8,
            "minEnchantmentLevel": 0,
            "maxEnchantmentLevel": 0,
            "affectedByFortune": false,
            "explosionDecay": false,
            "silkTouchMode": 0
          },
          {
            "type": "item",
            "item": {
              "value": "Items.COPPER_INGOT"
            },
            "weight": 1,
            "minCount": 13,
            "maxCount": 25,
            "minEnchantmentLevel": 0,
            "maxEnchantmentLevel": 0,
            "affectedByFortune": false,
            "explosionDecay": false,
            "silkTouchMode": 0
          },
          {
            "type": "item",
            "item": {
              "value": "CUSTOM:BronzeJug"
            },
            "weight": 1,
            "minCount": 1,
            "maxCount": 3,
            "minEnchantmentLevel": 0,
            "maxEnchantmentLevel": 0,
            "affectedByFortune": false,
            "explosionDecay": false,
            "silkTouchMode": 0
          },
          {
            "type": "item",
            "item": {
              "value": "CUSTOM:Zunbottle"
            },
            "weight": 1,
            "minCount": 1,
            "maxCount": 1,
            "minEnchantmentLevel": 0,
            "maxEnchantmentLevel": 0,
            "affectedByFortune": false,
            "explosionDecay": false,
            "silkTouchMode": 0
          }
        ]
      },
      {
        "minrolls": 1,
        "maxrolls": 2,
        "minbonusrolls": 0,
        "maxbonusrolls": 1,
        "hasbonusrolls": true,
        "entries": [
          {
            "type": "item",
            "item": {
              "value": "CUSTOM:WroughtPatternZun"
            },
            "weight": 1,
            "minCount": 1,
            "maxCount": 4,
            "minEnchantmentLevel": 0,
            "maxEnchantmentLevel": 0,
            "affectedByFortune": false,
            "explosionDecay": false,
            "silkTouchMode": 0
          },
          {
            "type": "item",
            "item": {
              "value": "CUSTOM:WroughtPatternJue"
            },
            "weight": 1,
            "minCount": 1,
            "maxCount": 4,
            "minEnchantmentLevel": 0,
            "maxEnchantmentLevel": 0,
            "affectedByFortune": false,
            "explosionDecay": false,
            "silkTouchMode": 0
          },
          {
            "type": "item",
            "item": {
              "value": "CUSTOM:WroughtPatternSmallDing"
            },
            "weight": 1,
            "minCount": 1,
            "maxCount": 4,
            "minEnchantmentLevel": 0,
            "maxEnchantmentLevel": 0,
            "affectedByFortune": false,
            "explosionDecay": false,
            "silkTouchMode": 0
          },
          {
            "type": "item",
            "item": {
              "value": "CUSTOM:WroughtPatternDou"
            },
            "weight": 1,
            "minCount": 1,
            "maxCount": 4,
            "minEnchantmentLevel": 0,
            "maxEnchantmentLevel": 0,
            "affectedByFortune": false,
            "explosionDecay": false,
            "silkTouchMode": 0
          },
          {
            "type": "item",
            "item": {
              "value": "CUSTOM:WroughtPatternYue"
            },
            "weight": 1,
            "minCount": 1,
            "maxCount": 4,
            "minEnchantmentLevel": 0,
            "maxEnchantmentLevel": 0,
            "affectedByFortune": false,
            "explosionDecay": false,
            "silkTouchMode": 0
          },
          {
            "type": "item",
            "item": {
              "value": "CUSTOM:WroughtPatternGui"
            },
            "weight": 1,
            "minCount": 1,
            "maxCount": 4,
            "minEnchantmentLevel": 0,
            "maxEnchantmentLevel": 0,
            "affectedByFortune": false,
            "explosionDecay": false,
            "silkTouchMode": 0
          },
          {
            "type": "item",
            "item": {
              "value": "CUSTOM:WroughtPatternDaggerAxe"
            },
            "weight": 1,
            "minCount": 1,
            "maxCount": 4,
            "minEnchantmentLevel": 0,
            "maxEnchantmentLevel": 0,
            "affectedByFortune": false,
            "explosionDecay": false,
            "silkTouchMode": 0
          }
        ]
      },
      {
        "minrolls": 1,
        "maxrolls": 1,
        "minbonusrolls": 1,
        "maxbonusrolls": 1,
        "hasbonusrolls": true,
        "entries": [
          {
            "type": "item",
            "item": {
              "value": "Items.IRON_INGOT"
            },
            "weight": 6,
            "minCount": 6,
            "maxCount": 12,
            "minEnchantmentLevel": 0,
            "maxEnchantmentLevel": 0,
            "affectedByFortune": false,
            "explosionDecay": false,
            "silkTouchMode": 0
          },
          {
            "type": "item",
            "item": {
              "value": "Items.IRON_HORSE_ARMOR"
            },
            "weight": 1,
            "minCount": 1,
            "maxCount": 1,
            "minEnchantmentLevel": 0,
            "maxEnchantmentLevel": 0,
            "affectedByFortune": false,
            "explosionDecay": false,
            "silkTouchMode": 0
          },
          {
            "type": "item",
            "item": {
              "value": "Items.IRON_HOE"
            },
            "weight": 3,
            "minCount": 1,
            "maxCount": 1,
            "minEnchantmentLevel": 1,
            "maxEnchantmentLevel": 3,
            "affectedByFortune": false,
            "explosionDecay": false,
            "silkTouchMode": 0
          }
        ]
      },
      {
        "minrolls": 1,
        "maxrolls": 1,
        "minbonusrolls": 1,
        "maxbonusrolls": 1,
        "hasbonusrolls": true,
        "entries": [
          {
            "type": "item",
            "item": {
              "value": "Items.GOLD_INGOT"
            },
            "weight": 6,
            "minCount": 2,
            "maxCount": 5,
            "minEnchantmentLevel": 0,
            "maxEnchantmentLevel": 0,
            "affectedByFortune": false,
            "explosionDecay": false,
            "silkTouchMode": 0
          },
          {
            "type": "item",
            "item": {
              "value": "Items.GOLDEN_APPLE#0"
            },
            "weight": 2,
            "minCount": 1,
            "maxCount": 3,
            "minEnchantmentLevel": 0,
            "maxEnchantmentLevel": 0,
            "affectedByFortune": false,
            "explosionDecay": false,
            "silkTouchMode": 0
          },
          {
            "type": "item",
            "item": {
              "value": "Items.GOLDEN_CARROT"
            },
            "weight": 8,
            "minCount": 4,
            "maxCount": 8,
            "minEnchantmentLevel": 0,
            "maxEnchantmentLevel": 0,
            "affectedByFortune": false,
            "explosionDecay": false,
            "silkTouchMode": 0
          },
          {
            "type": "item",
            "item": {
              "value": "Items.GOLDEN_HORSE_ARMOR"
            },
            "weight": 1,
            "minCount": 1,
            "maxCount": 1,
            "minEnchantmentLevel": 0,
            "maxEnchantmentLevel": 0,
            "affectedByFortune": false,
            "explosionDecay": false,
            "silkTouchMode": 0
          },
          {
            "type": "item",
            "item": {
              "value": "Items.GOLD_NUGGET"
            },
            "weight": 7,
            "minCount": 2,
            "maxCount": 5,
            "minEnchantmentLevel": 0,
            "maxEnchantmentLevel": 0,
            "affectedByFortune": false,
            "explosionDecay": false,
            "silkTouchMode": 0
          }
        ]
      },
      {
        "minrolls": 1,
        "maxrolls": 1,
        "minbonusrolls": 1,
        "maxbonusrolls": 1,
        "hasbonusrolls": false,
        "entries": [
          {
            "type": "item",
            "item": {
              "value": "Items.SADDLE"
            },
            "weight": 1,
            "minCount": 0,
            "maxCount": 1,
            "minEnchantmentLevel": 0,
            "maxEnchantmentLevel": 0,
            "affectedByFortune": false,
            "explosionDecay": false,
            "silkTouchMode": 0
          }
        ]
      },
      {
        "minrolls": 1,
        "maxrolls": 1,
        "minbonusrolls": 0,
        "maxbonusrolls": 1,
        "hasbonusrolls": true,
        "entries": [
          {
            "type": "item",
            "item": {
              "value": "Items.DIAMOND"
            },
            "weight": 5,
            "minCount": 1,
            "maxCount": 3,
            "minEnchantmentLevel": 0,
            "maxEnchantmentLevel": 0,
            "affectedByFortune": false,
            "explosionDecay": false,
            "silkTouchMode": 0
          },
          {
            "type": "item",
            "item": {
              "value": "Items.DIAMOND_HORSE_ARMOR"
            },
            "weight": 2,
            "minCount": 1,
            "maxCount": 1,
            "minEnchantmentLevel": 0,
            "maxEnchantmentLevel": 0,
            "affectedByFortune": false,
            "explosionDecay": false,
            "silkTouchMode": 0
          },
          {
            "type": "item",
            "item": {
              "value": "Items.DIAMOND_SWORD"
            },
            "weight": 3,
            "minCount": 1,
            "maxCount": 1,
            "minEnchantmentLevel": 0,
            "maxEnchantmentLevel": 4,
            "affectedByFortune": false,
            "explosionDecay": false,
            "silkTouchMode": 0
          }
        ]
      }
    ],
    "name": "chests/ancient_grave_2",
    "namespace": "mod"
  }
}