{
  "_fv": 66,
  "_type": "achievement",
  "definition": {
    "achievementName": "Ancient books that be made in yesterday",
    "achievementDescription": "Make thе knowledge bamboo slips and wave it",
    "achievementIcon": {
      "value": "CUSTOM:KnowledgeBambooSlips"
    },
    "background": "Default",
    "disableDisplay": false,
    "showPopup": true,
    "announceToChat": true,
    "hideIfNotCompleted": true,
    "rewardLoot": [],
    "rewardRecipes": [
      "Fdsjc",
      "Dsfdsddssd",
      "Fdfdd",
      "Sdsddssdds",
      "Ssdfghjkl",
      "Ajpihdalskhd",
      "Dsdsdsds",
      "Maker",
      "Sadsdssa",
      "GHIkhihiuys",
      "Aassasa",
      "Sssssssssss",
      "Fdffdgfh",
      "Sasajikoi",
      "Saasiasfdi",
      "Sdfgh",
      "Siru8ui8",
      "Konwuswords",
      "Sad",
      "Ger",
      "Jades",
      "Jadeblocksmake",
      "NewStickCrafting",
      "DIpoils",
      "Cookfishforit",
      "Dkdkdkkd",
      "HuangGuanSlabRecipe",
      "HuangGuanStairsRecipe",
      "Basketforzhou",
      "Sdfghjkgfgf",
      "Oilvinesmakersssssssss123",
      "TheBloodCopperArmorChestplateRecipe",
      "Sangtapdoors",
      "MetasequoiaPlanksLogRecipe",
      "TheBloodCopperArmorLeggingsRecipe",
      "TheBloodCopperArmorBootsRecipe",
      "Foxcook",
      "MetasequoiaStairsRecipe",
      "XuandeChestplate",
      "Tjhedhhsadoor",
      "UnderRockmaker1",
      "Cookspaceplaces",
      "Knowlegessss",
      "UnderIronArmor4",
      "YanWoodRecipe",
      "PeachBlossomWoodRecipe",
      "BloodCopper114514",
      "UnderIron4b",
      "UnderIronArmor2",
      "UnderIronArmor1",
      "OilVinesmaker",
      "Oilsmaker",
      "UndersOres",
      "UnderIronItem",
      "PlagueHalberds",
      "RedruFishMeat",
      "HuangGuanFenceGateRecipe",
      "PanPressurePlateRecipe",
      "YanStairsRecipe",
      "Tailsmakerxssss",
      "PanWoodRecipe",
      "Huangdguande",
      "CopperCutterA"
    ],
    "rewardFunction": "No function",
    "rewardXP": 0,
    "achievementType": "goal",
    "parent": {
      "value": "CUSTOM:CollectJade"
    },
    "triggerxml": "<?xml version=\"1.0\" encoding=\"UTF-8\" standalone=\"no\"?><xml xmlns=\"https://developers.google.com/blockly/xml\"><block deletable=\"false\" type=\"advancement_trigger\" x=\"40\" y=\"80\"><next><block type=\"custom_trigger\" x=\"48\" y=\"52\"/></next></block></xml>"
  }
}