{
  "_fv": 66,
  "_type": "recipe",
  "definition": {
    "recipeType": "Crafting",
    "recipeRetstackSize": 5,
    "group": "",
    "cookingBookCategory": "MISC",
    "xpReward": 0.0,
    "cookingTime": 200,
    "craftingBookCategory": "MISC",
    "recipeShapeless": false,
    "recipeSlots": [
      {
        "value": "Items.GOLD_NUGGET"
      },
      {
        "value": "CUSTOM:ShatangFruit"
      },
      {
        "value": "Items.GOLD_NUGGET"
      },
      {
        "value": "CUSTOM:ShatangFruit"
      },
      {
        "value": "CUSTOM:ShatangFruit"
      },
      {
        "value": "CUSTOM:ShatangFruit"
      },
      {
        "value": "Items.GOLD_NUGGET"
      },
      {
        "value": "CUSTOM:ShatangFruit"
      },
      {
        "value": "Items.GOLD_NUGGET"
      }
    ],
    "recipeReturnStack": {
      "value": "CUSTOM:GoldenShatangFruit"
    },
    "name": "golden_shatang_fruits",
    "namespace": "mod"
  }
}