{
	"format_version": "1.8.0",
	"animations": {
		"idle": {
			"loop": true,
			"animation_length": 1.4,
			"bones": {
				"leg": {
					"rotation": {
						"0.0": [0, 0, 0],
						"0.44": [5, 0, 0],
						"0.96": [0, 0, 0]
					}
				},
				"rightSleeve": {
					"rotation": {
						"0.0": [0, 0, -2.5],
						"0.76": [0, 0, -7.5],
						"1.4": [0, 0, -2.5]
					}
				},
				"leftSleeve": {
					"rotation": {
						"0.0": [0, 0, -2.5],
						"0.76": [0, 0, 5],
						"1.4": [0, 0, -2.5]
					}
				},
				"tongue": {
					"rotation": {
						"0.0": [0, 0, 0],
						"0.44": [5, 0, 0],
						"1.4": [0, 0, 0]
					}
				},
				"tongue2": {
					"rotation": {
						"0.0": [0, 0, 0],
						"0.44": [-15, 0, 0],
						"1.4": [0, 0, 0]
					}
				},
				"tongue3": {
					"rotation": {
						"0.0": [0, 0, 0],
						"0.44": [-17.5, 0, 0],
						"1.4": [0, 0, 0]
					}
				}
			}
		},
		"walk": {
			"loop": true,
			"animation_length": 1,
			"bones": {
				"leg": {
					"rotation": {
						"0.0": {
							"vector": [0, 0, 0]
						},
						"0.24": {
							"vector": [0, 0, 2.5]
						},
						"0.44": {
							"vector": [0, 0, 0]
						},
						"0.68": {
							"vector": [0, 0, -2.5]
						},
						"1.0": {
							"vector": [0, 0, 0]
						}
					},
					"scale": {
						"vector": [1, 1, 1]
					}
				},
				"rightSleeve": {
					"rotation": {
						"0.0": {
							"vector": [0, 0, 0]
						},
						"0.24": {
							"vector": [-12.5, 0, -2.5]
						},
						"0.44": {
							"vector": [0, 0, 0]
						},
						"0.68": {
							"vector": [17.5, 0, 2.5]
						},
						"1.0": {
							"vector": [0, 0, 0]
						}
					}
				},
				"leftSleeve": {
					"rotation": {
						"0.0": {
							"vector": [0, 0, 0]
						},
						"0.24": {
							"vector": [17.5, 0, -2.5]
						},
						"0.44": {
							"vector": [0, 0, 0]
						},
						"0.68": {
							"vector": [-12.5, 0, 2.5]
						},
						"1.0": {
							"vector": [0, 0, 0]
						}
					}
				},
				"head": {
					"rotation": {
						"0.0": {
							"vector": [0, 0, 0]
						},
						"0.24": {
							"vector": [0, 0, -2.5]
						},
						"0.44": {
							"vector": [0, 0, 0]
						},
						"0.68": {
							"vector": [0, 0, 2.5]
						},
						"1.0": {
							"vector": [0, 0, 0]
						}
					}
				},
				"left_leg": {
					"rotation": {
						"0.0": {
							"vector": [-7.5, 0, 0]
						},
						"0.44": {
							"vector": [5, 0, 0]
						},
						"1.0": {
							"vector": [-7.5, 0, 0]
						}
					}
				},
				"right_leg2": {
					"rotation": {
						"0.0": {
							"vector": [5, 0, 0]
						},
						"0.44": {
							"vector": [-5, 0, 0]
						},
						"1.0": {
							"vector": [5, 0, 0]
						}
					}
				},
				"ear": {
					"rotation": {
						"0.0": {
							"vector": [0, 0, 0]
						},
						"0.4": {
							"vector": [0, 0, -5]
						},
						"1.0": {
							"vector": [0, 0, 0]
						}
					}
				},
				"ear2": {
					"rotation": {
						"0.0": {
							"vector": [0, 0, 0]
						},
						"0.4": {
							"vector": [0, 0, 5]
						},
						"1.0": {
							"vector": [0, 0, 0]
						}
					}
				}
			}
		},
		"attack": {
			"animation_length": 0.92,
			"bones": {
				"rightSleeve": {
					"rotation": {
						"0.0": {
							"vector": [0, 0, 0]
						},
						"0.2": {
							"vector": [-92.97576, 9.8701, -2.97576]
						},
						"0.72": {
							"vector": [-92.98, 9.87, -2.98]
						},
						"0.88": {
							"vector": [0, 0, 0]
						}
					},
					"position": {
						"0.0": {
							"vector": [0, 0, 0]
						},
						"0.12": {
							"vector": [0, 0, -2]
						},
						"0.28": {
							"vector": [0, 0, 2.2]
						},
						"0.48": {
							"vector": [0, 0, -2]
						},
						"0.72": {
							"vector": [0, 0, 0]
						}
					}
				},
				"leftSleeve": {
					"rotation": {
						"0.0": {
							"vector": [0, 0, 0]
						},
						"0.2": {
							"vector": [-90.44067, -9.99038, 2.53852]
						},
						"0.72": {
							"vector": [-90.44, -9.99, 2.54]
						},
						"0.88": {
							"vector": [0, 0, 0]
						}
					},
					"position": {
						"0.12": {
							"vector": [0, 0, 0.6]
						},
						"0.28": {
							"vector": [1.6, 0, -2.6]
						},
						"0.44": {
							"vector": [0, 0, -0.9]
						},
						"0.6": {
							"vector": [0, 0, -2]
						},
						"0.8": {
							"vector": [0, 0, -0.9]
						}
					}
				},
				"head": {
					"rotation": {
						"0.12": {
							"vector": [0, 0, 0]
						},
						"0.24": {
							"vector": [-1.5, 0, 0]
						},
						"0.36": {
							"vector": [0, 0, 0]
						},
						"0.48": {
							"vector": [-1.5, 0, 0]
						},
						"0.6": {
							"vector": [0, 0, 0]
						},
						"0.72": {
							"vector": [-1.5, 0, 0]
						}
					}
				},
				"leg": {
					"rotation": {
						"0.0": {
							"vector": [0, 0, 0]
						},
						"0.2": {
							"vector": [1, 0, 0]
						},
						"0.36": {
							"vector": [0, 0, 0]
						},
						"0.48": {
							"vector": [1, 0, 0]
						},
						"0.6": {
							"vector": [0, 0, 0]
						},
						"0.72": {
							"vector": [1, 0, 0]
						}
					}
				}
			}
		},
		"hurt": {
			"animation_length": 0.4,
			"bones": {
				"rightSleeve": {
					"rotation": {
						"0.0": {
							"vector": [0, 0, 0]
						},
						"0.24": {
							"vector": [16.73634, 5.188, -16.73634]
						},
						"0.4": {
							"vector": [0, 0, 0]
						}
					}
				},
				"leftSleeve": {
					"rotation": {
						"0.0": {
							"vector": [0, 0, 0]
						},
						"0.24": {
							"vector": [16.73634, -5.188, 16.73634]
						},
						"0.4": {
							"vector": [0, 0, 0]
						}
					}
				},
				"tongue": {
					"rotation": {
						"0.0": {
							"vector": [0, 0, 0]
						},
						"0.24": {
							"vector": [17.5, 0, 0]
						},
						"0.4": {
							"vector": [0, 0, 0]
						}
					}
				},
				"tongue2": {
					"rotation": {
						"0.0": {
							"vector": [0, 0, 0]
						},
						"0.2": {
							"vector": [17.5, 0, 0]
						},
						"0.4": {
							"vector": [0, 0, 0]
						}
					}
				},
				"tongue3": {
					"rotation": {
						"0.0": {
							"vector": [0, 0, 0]
						},
						"0.2": {
							"vector": [20, 0, 0]
						},
						"0.4": {
							"vector": [0, 0, 0]
						}
					}
				}
			}
		},
		"wave": {
			"animation_length": 1.4,
			"bones": {
				"ear": {
					"rotation": {
						"0.0": [0, 0, 0],
						"0.36": [0, 0, -22.5],
						"0.72": [0, 0, 0],
						"1.08": [0, 0, -22.5],
						"1.4": [0, 0, 0]
					}
				},
				"ear2": {
					"rotation": {
						"0.0": [0, 0, 0],
						"0.36": [0, 0, 22.5],
						"0.72": [0, 0, 0],
						"1.08": [0, 0, 22.5],
						"1.4": [0, 0, 0]
					}
				},
				"body": {
					"rotation": {
						"0.0": [0, 0, 0],
						"0.36": [-2.4905, 0.21782, 4.99527],
						"0.72": [0, 0, 0],
						"1.08": [2.4905, 0.21782, -4.99527],
						"1.4": [0, 0, 0]
					}
				},
				"rightSleeve": {
					"rotation": {
						"0.0": [0, 0, 0],
						"0.36": [-15, 0, -132.5],
						"0.6": [-35, 0, -117.5],
						"0.84": [-24.0724, -8.53726, -129.87961],
						"1.04": [-25.13121, 4.19332, -102.63819],
						"1.4": [0, 0, 0]
					}
				},
				"leftSleeve": {
					"rotation": {
						"0.0": [0, 0, 0],
						"0.36": [-15, 0, 132.5],
						"0.6": [-35, 0, 117.5],
						"0.84": [-24.0724, 8.53726, 129.87961],
						"1.04": [-25.13121, -4.19332, 102.63819],
						"1.4": [0, 0, 0]
					}
				}
			}
		},
		"sprint": {
			"loop": true,
			"animation_length": 0.68,
			"bones": {
				"leg": {
					"rotation": {
						"0.0": [0, 0, 0],
						"0.12": [0, 0, 2.5],
						"0.28": [0, 0, 0],
						"0.48": [0, 0, -2.5],
						"0.68": [0, 0, 0]
					},
					"scale": 1
				},
				"rightSleeve": {
					"rotation": {
						"0.0": [0, 0, 0],
						"0.12": [-12.5, 0, -2.5],
						"0.28": [0, 0, 0],
						"0.48": [29.47028, 14.36495, -21.20348],
						"0.68": [0, 0, 0]
					}
				},
				"leftSleeve": {
					"rotation": {
						"0.0": [0, 0, 0],
						"0.12": [29.47028, -14.36495, 21.20348],
						"0.28": [0, 0, 0],
						"0.48": [-12.5, 0, 2.5],
						"0.68": [0, 0, 0]
					}
				},
				"head": {
					"rotation": {
						"0.0": [0, 0, 0],
						"0.12": [0, 0, -2.5],
						"0.28": [0, 0, 0],
						"0.48": [0, 0, 2.5],
						"0.68": [0, 0, 0]
					},
					"position": {
						"0.0": [0, 0, 0],
						"0.12": [0, 0.7, 0],
						"0.28": [0, 0, 0],
						"0.48": [0, 0.7, 0],
						"0.68": [0, 0, 0]
					}
				},
				"left_leg": {
					"rotation": {
						"0.0": [-7.5, 0, 0],
						"0.32": [5, 0, 0],
						"0.68": [-7.5, 0, 0]
					}
				},
				"right_leg2": {
					"rotation": {
						"0.0": [5, 0, 0],
						"0.32": [-5, 0, 0],
						"0.68": [5, 0, 0]
					}
				},
				"ear": {
					"rotation": {
						"0.0": [0, 0, 0],
						"0.32": [0, 0, -5],
						"0.68": [0, 0, 0]
					}
				},
				"ear2": {
					"rotation": {
						"0.0": [0, 0, 0],
						"0.32": [0, 0, 5],
						"0.68": [0, 0, 0]
					}
				}
			}
		}
	},
	"geckolib_format_version": 2
}